{
    "$schema": "https://get.aiware.com/schemas/v2/aion/schema",
    "$comment": "Anomaly document containing anomaly objects and series.",
    "validationContracts": [
        "anomaly"
    ],
    "object": [
        {
            "type": "anomaly",
            "objectCategory": [
                {
                    "class": "anomaly",
                    "@id": "12345",
                    "confidence": 0.468
                }
            ]
        },
        {
            "type": "anomaly",
            "objectCategory": [
                {
                    "class": "anomaly",
                    "@id": "7665554",
                    "confidence": 0.903
                }
            ]
        }
    ],
    "series": [
        {
            "startTimeMs": 1243,
            "stopTimeMs": 2120,
            "object": {
                "type": "anomaly",
                "objectCategory": [
                    {
                        "class": "anomaly",
                        "@id": "12345",
                        "confidence": 0.468
                    }
                ]
            }
        },
        {
            "startTimeMs": 2244,
            "stopTimeMs": 3456,
            "object": {
                "type": "anomaly",
                "objectCategory": [
                    {
                        "class": "anomaly",
                        "@id": "803263",
                        "confidence": 0.895
                    }
                ]
            }
        }
    ]
}